hvsrprocpy/__init__.py
hvsrprocpy/fdt.py
hvsrprocpy/hvhelp.py
hvsrprocpy/hvplt.py
hvsrprocpy/hvsrmetatools.py
hvsrprocpy/hvsrprocall.py
hvsrprocpy/hvt.py
hvsrprocpy/meta.py
hvsrprocpy/tdt.py
hvsrprocpy-1.1.0.dist-info/LICENSE.txt
hvsrprocpy-1.1.0.dist-info/METADATA
hvsrprocpy-1.1.0.dist-info/WHEEL
hvsrprocpy-1.1.0.dist-info/top_level.txt
hvsrprocpy-1.1.0.dist-info/RECORD
