Metadata-Version: 2.1
Name: hvsrprocpy
Version: 1.1.0
Summary: A python library for performing horizontal-to-vertical spectral ratio (HVSR) processing
Home-page: https://github.com/fjornelas/hvsrprocpy
Author: Francisco Javier Ornelas
Author-email: jornela1@g.ucla.edu
License: GNU General Public License v3
Project-URL: Bug Reports, https://github.com/fjornelas/hvsrprocpy/issues
Project-URL: Source, https://github.com/fjornelas/hvsrprocpy/
Project-URL: Docs, https://fjornelas.github.io/hvsrprocpy/
Keywords: HVSR,FAS,Time Series,microtremors
Classifier: Development Status :: 5 - Production/Stable
Classifier: Intended Audience :: Developers
Classifier: Intended Audience :: Education
Classifier: Intended Audience :: Science/Research
Classifier: Topic :: Education
Classifier: Topic :: Scientific/Engineering
Classifier: Topic :: Scientific/Engineering :: Physics
Classifier: License :: OSI Approved :: GNU General Public License v3 (GPLv3)
Classifier: Natural Language :: English
Classifier: Programming Language :: Python :: 3.8
Classifier: Programming Language :: Python :: 3.9
Classifier: Topic :: Software Development :: Version Control :: Git
Requires-Python: >=3.8
License-File: LICENSE.txt
Requires-Dist: numpy >=1.20
Requires-Dist: pandas
Requires-Dist: matplotlib
Requires-Dist: obspy
Requires-Dist: scipy
Requires-Dist: parzenpy
